SimiLab/SimiLab.py
SimiLab/__init__.py
SimilarityLab-0.0.5.1.dist-info/METADATA
SimilarityLab-0.0.5.1.dist-info/WHEEL
SimilarityLab-0.0.5.1.dist-info/top_level.txt
SimilarityLab-0.0.5.1.dist-info/RECORD
