Metadata-Version: 2.1
Name: SimilarityLab
Version: 0.0.5.1
Summary: NPL Package in development
Home-page: https://github.com/CID-ITBA
Author: CID
Author-email: author@example.com
License: MIT
Keywords: NLP corpus meaning
Platform: UNKNOWN
Classifier: Programming Language :: Python :: 3
Classifier: License :: OSI Approved :: MIT License
Classifier: Operating System :: OS Independent
Requires-Python: >=3.6
Requires-Dist: numpy
Requires-Dist: scipy
